pykk-0.1.8.dist-info/METADATA
pykk-0.1.8.dist-info/WHEEL
pykk-0.1.8.dist-info/licenses/LICENCE.txt
pykk/__init__.py
pykk/pykk.cpython-314-s390x-linux-gnu.so
pykk-0.1.8.dist-info/RECORD
