Metadata-Version: 2.4
Name: pykk
Version: 0.1.8
Classifier: Programming Language :: Rust
Classifier: Programming Language :: Python :: Implementation :: CPython
Classifier: Programming Language :: Python :: Implementation :: PyPy
License-File: LICENCE.txt
Summary: Fast Kramers-Kronig transform library written in Rust
Home-Page: http://github.com/Hayashi-Yudai/pykk
Requires-Python: >=3.10, <3.15
